kineticpdf/__init__.py
kineticpdf/buildxobj.py
kineticpdf/compress.py
kineticpdf/crypt.py
kineticpdf/errors.py
kineticpdf/findobjs.py
kineticpdf/pagemerge.py
kineticpdf/pdfreader.py
kineticpdf/pdfwriter.py
kineticpdf/pike.py
kineticpdf/py23_diffs.py
kineticpdf/pypdf2.py
kineticpdf/tokens.py
kineticpdf/toreportlib.py
kineticpdf/uncompress.py
kineticpdf/kinetic/__init__.py
kineticpdf/objects/__init__.py
kineticpdf/objects/pdfarray.py
kineticpdf/objects/pdfdict.py
kineticpdf/objects/pdfindirect.py
kineticpdf/objects/pdfname.py
kineticpdf/objects/pdfobject.py
kineticpdf/objects/pdfstring.py
kineticpdf/pdf2/__init__.py
kineticpdf/pdf2/_cmap.py
kineticpdf/pdf2/_encryption.py
kineticpdf/pdf2/_merger.py
kineticpdf/pdf2/_page.py
kineticpdf/pdf2/_protocols.py
kineticpdf/pdf2/_reader.py
kineticpdf/pdf2/_security.py
kineticpdf/pdf2/_utils.py
kineticpdf/pdf2/_version.py
kineticpdf/pdf2/_writer.py
kineticpdf/pdf2/constants.py
kineticpdf/pdf2/errors.py
kineticpdf/pdf2/filters.py
kineticpdf/pdf2/pagerange.py
kineticpdf/pdf2/papersizes.py
kineticpdf/pdf2/types.py
kineticpdf/pdf2/xmp.py
kineticpdf/pdf2/_codecs/__init__.py
kineticpdf/pdf2/_codecs/adobe_glyphs.py
kineticpdf/pdf2/_codecs/pdfdoc.py
kineticpdf/pdf2/_codecs/std.py
kineticpdf/pdf2/_codecs/symbol.py
kineticpdf/pdf2/_codecs/zapfding.py
kineticpdf/pdf2/generic/__init__.py
kineticpdf/pdf2/generic/_annotations.py
kineticpdf/pdf2/generic/_base.py
kineticpdf/pdf2/generic/_data_structures.py
kineticpdf/pdf2/generic/_fit.py
kineticpdf/pdf2/generic/_outline.py
kineticpdf/pdf2/generic/_rectangle.py
kineticpdf/pdf2/generic/_utils.py
kineticpdf-0.0.25.dist-info/METADATA
kineticpdf-0.0.25.dist-info/WHEEL
kineticpdf-0.0.25.dist-info/top_level.txt
kineticpdf-0.0.25.dist-info/RECORD
