Metadata-Version: 2.1
Name: kineticpdf
Version: 0.0.25
Summary: Read/Write PDF Text, Forms, and Metadata.
Author: Kinetic Seas (Ed Honour / Joe Lehman), pdfrw, pypdf2
Author-email: <edward.honour@kineticseas.com>
Keywords: python,PDF,PDFForms,extract PDF text,extract PDF Form fields
Classifier: Development Status :: 4 - Beta
Classifier: Intended Audience :: Developers
Classifier: Programming Language :: Python :: 3
Classifier: Operating System :: Unix
Classifier: Operating System :: MacOS :: MacOS X
Classifier: Operating System :: Microsoft :: Windows
Requires-Dist: pycryptodome
Requires-Dist: pikepdf
